md_to_html2/__init__.py
md_to_html2/cli.py
md_to_html2/config.yaml
md_to_html2/convert.py
md_to_html2/helpers.py
md_to_html2/j2x.py
md_to_html2/mdx.py
md_to_html2/templates/lightgallery.j2
md_to_html2/templates/navright.j2
md_to_html2/templates/revealjs-highlight.j2
md_to_html2/templates/revealjs.j2
md_to_html2/templates/simple.j2
md_to_html2/templates/shared/codehilite.css
md_to_html2/templates/shared/justify.css
md_to_html2/templates/shared/mathjax-config.js
md_to_html2/templates/shared/navright.css
md_to_html2/templates/shared/styles.css
md_to_html2/templates/shared/themeswitch.js
md_to_html2-0.3.dist-info/LICENCE
md_to_html2-0.3.dist-info/METADATA
md_to_html2-0.3.dist-info/WHEEL
md_to_html2-0.3.dist-info/entry_points.txt
md_to_html2-0.3.dist-info/top_level.txt
md_to_html2-0.3.dist-info/RECORD
