Metadata-Version: 2.1
Name: md-to-html2
Version: 0.3
Summary: Convert Markdown to HTML using Jinja2 templates
Author-email: gi1242 <gi1242+mdtohtml@gmail.com>
Project-URL: Homepage, https://codeberg.org/gi1242/md-to-html
Classifier: Programming Language :: Python :: 3
Classifier: License :: OSI Approved :: MIT License
Classifier: Operating System :: OS Independent
Classifier: Development Status :: 4 - Beta
Classifier: Topic :: Text Processing :: Markup :: Markdown
Classifier: Topic :: Text Processing :: Markup :: HTML
Classifier: Topic :: Multimedia :: Graphics :: Presentation
Requires-Python: >=3.10
License-File: LICENCE
Requires-Dist: python-frontmatter >=1.0.0
Requires-Dist: Jinja2 >=3.1.2
Requires-Dist: Markdown >=3.5.1
Requires-Dist: pyxdg >=0.28
Requires-Dist: MarkupSafe >=2.1.3
Provides-Extra: codehilite
Requires-Dist: Pygments >=2.17.2 ; extra == 'codehilite'
Provides-Extra: resize
Requires-Dist: Pillow >=10.1.0 ; extra == 'resize'
